{
  "BYTES_DELETED": "0",
  "BYTES_READ_FROM_RESULT": "0",
  "BYTES_SCANNED": "0",
  "BYTES_SENT_OVER_THE_NETWORK": "0",
  "BYTES_SPILLED_TO_LOCAL_STORAGE": "0",
  "BYTES_SPILLED_TO_REMOTE_STORAGE": "0",
  "BYTES_WRITTEN": "0",
  "BYTES_WRITTEN_TO_RESULT": "36",
  "CHILD_QUERIES_WAIT_TIME": "0",
  "CLUSTER_NUMBER": null,
  "COMPILATION_TIME": "19",
  "CREDITS_USED_CLOUD_SERVICES": "7.9999999999999996e-06",
  "DATABASE_ID": null,
  "DATABASE_NAME": null,
  "END_TIME": "1716999270.704000",
  "ERROR_CODE": null,
  "ERROR_MESSAGE": null,
  "EXECUTION_STATUS": "SUCCESS",
  "EXECUTION_TIME": "36",
  "EXTERNAL_FUNCTION_TOTAL_INVOCATIONS": "0",
  "EXTERNAL_FUNCTION_TOTAL_RECEIVED_BYTES": "0",
  "EXTERNAL_FUNCTION_TOTAL_RECEIVED_ROWS": "0",
  "EXTERNAL_FUNCTION_TOTAL_SENT_BYTES": "0",
  "EXTERNAL_FUNCTION_TOTAL_SENT_ROWS": "0",
  "FAULT_HANDLING_TIME": null,
  "INBOUND_DATA_TRANSFER_BYTES": "0",
  "INBOUND_DATA_TRANSFER_CLOUD": null,
  "INBOUND_DATA_TRANSFER_REGION": null,
  "IS_CLIENT_GENERATED_STATEMENT": "false",
  "LIST_EXTERNAL_FILES_TIME": "0",
  "OUTBOUND_DATA_TRANSFER_BYTES": "0",
  "OUTBOUND_DATA_TRANSFER_CLOUD": null,
  "OUTBOUND_DATA_TRANSFER_REGION": null,
  "PARTITIONS_SCANNED": "0",
  "PARTITIONS_TOTAL": "0",
  "PERCENTAGE_SCANNED_FROM_CACHE": "0",
  "QUERY_ACCELERATION_BYTES_SCANNED": "0",
  "QUERY_ACCELERATION_PARTITIONS_SCANNED": "0",
  "QUERY_ACCELERATION_UPPER_LIMIT_SCALE_FACTOR": "0",
  "QUERY_HASH": "fdac6a14c32fdac6a14c32fda",
  "QUERY_HASH_VERSION": "2",
  "QUERY_ID": "01b4a7ce-0000-66gh-0000-65165115a3bda",
  "QUERY_LOAD_PERCENT": null,
  "QUERY_PARAMETERIZED_HASH": "fdac6a14c32fdac6a14c32fda",
  "QUERY_PARAMETERIZED_HASH_VERSION": "1",
  "QUERY_RETRY_CAUSE": null,
  "QUERY_RETRY_TIME": null,
  "QUERY_TAG": "",
  "QUERY_TEXT": "grant ownership on database VILLIANS_DB to role GOTHAM_ADMINS_ROLE copy current grants;",
  "QUERY_TYPE": "GRANT",
  "QUEUED_OVERLOAD_TIME": "0",
  "QUEUED_PROVISIONING_TIME": "0",
  "QUEUED_REPAIR_TIME": "0",
  "RELEASE_VERSION": "8.21.1",
  "ROLE_NAME": "BRUCE_WAYNE_ROLE",
  "ROLE_TYPE": "ROLE",
  "ROWS_DELETED": "0",
  "ROWS_INSERTED": "0",
  "ROWS_PRODUCED": null,
  "ROWS_UNLOADED": "0",
  "ROWS_UPDATED": "0",
  "ROWS_WRITTEN_TO_RESULT": "1",
  "SCHEMA_ID": null,
  "SCHEMA_NAME": null,
  "SECONDARY_ROLE_STATS": "{\"roleNames\":[],\"roleCount\":0,\"roleIds\":[]}",
  "SESSION_ID": "47121867651652",
  "START_TIME": "1716999270.649000",
  "TOTAL_ELAPSED_TIME": "55",
  "TRANSACTION_BLOCKED_TIME": "0",
  "TRANSACTION_ID": "0",
  "USER_NAME": "ALFRED_ADMIN",
  "WAREHOUSE_ID": "1",
  "WAREHOUSE_NAME": "GOTHAM_WAREHOUSE",
  "WAREHOUSE_SIZE": null,
  "WAREHOUSE_TYPE": "STANDARD"
}